Metadata-Version: 2.1
Name: scastpy
Version: 0.0.3
Summary: A simple digital media player written by Python
Home-page: https://github.com/RicterZ/scastpy
Author: Ricter Z <ricterzheng@gmail.com>
Author-email: ricterzheng@gmail.com
License: MIT
Download-URL: https://github.com/RicterZ/scastpy/tarball/master
Keywords: DLNA,ScreenCast,SSDP,Media Player
Platform: UNKNOWN
License-File: LICENSE
